stylelens_admin
