Metadata-Version: 1.0
Name: stylelens-admin
Version: 0.0.3
Summary: db-admin
Home-page: UNKNOWN
Author: UNKNOWN
Author-email: master@bluehack.net
License: UNKNOWN
Keywords: BlueLens,db-admin
Platform: UNKNOWN
